chakra_py/__init__.py
chakra_py/client.py
chakra_py/exceptions.py
chakra_py-1.0.24.dist-info/LICENSE
chakra_py-1.0.24.dist-info/METADATA
chakra_py-1.0.24.dist-info/WHEEL
chakra_py-1.0.24.dist-info/RECORD
